chess/__init__.py
chess/_interactive.py
chess/engine.py
chess/gaviota.py
chess/pgn.py
chess/polyglot.py
chess/py.typed
chess/svg.py
chess/syzygy.py
chess/variant.py
chess-1.6.0.dist-info/LICENSE.txt
chess-1.6.0.dist-info/METADATA
chess-1.6.0.dist-info/WHEEL
chess-1.6.0.dist-info/top_level.txt
chess-1.6.0.dist-info/RECORD
