Metadata-Version: 2.1
Name: chess
Version: 1.6.0
Summary: A chess library with move generation and validation, Polyglot opening book probing, PGN reading and writing, Gaviota tablebase probing, Syzygy tablebase probing, and XBoard/UCI engine communication.
Home-page: https://github.com/niklasf/python-chess
Author: Niklas Fiekas
Author-email: niklas.fiekas@backscattering.de
License: GPL-3.0+
Project-URL: Documentation, https://python-chess.readthedocs.io
Keywords: chess fen epd pgn polyglot syzygy gaviota uci xboard
Platform: UNKNOWN
Classifier: Development Status :: 5 - Production/Stable
Classifier: Intended Audience :: Developers
Classifier: Intended Audience :: Science/Research
Classifier: License :: OSI Approved :: GNU General Public License v3 or later (GPLv3+)
Classifier: Operating System :: OS Independent
Classifier: Programming Language :: Python :: 3 :: Only
Classifier: Programming Language :: Python :: 3.7
Classifier: Programming Language :: Python :: 3.8
Classifier: Programming Language :: Python :: 3.9
Classifier: Programming Language :: Python :: 3.10
Classifier: Topic :: Games/Entertainment :: Board Games
Classifier: Topic :: Games/Entertainment :: Turn Based Strategy
Classifier: Topic :: Software Development :: Libraries :: Python Modules
Classifier: Typing :: Typed
Obsoletes: python_chess
Requires-Python: >=3.7
License-File: LICENSE.txt
